objclick/__init__.py
objclick/decorators.py
objclick/objclick.py
objclick-0.1.1.dist-info/LICENSE
objclick-0.1.1.dist-info/METADATA
objclick-0.1.1.dist-info/WHEEL
objclick-0.1.1.dist-info/top_level.txt
objclick-0.1.1.dist-info/RECORD
