Metadata-Version: 2.1
Name: objclick
Version: 0.1.1
Summary: provides a drop-in replacement for click, extending it to work in various OOP contexts
Home-page: https://gitlab.com/embray/objclick
Author: E. Madison Bray
License: MIT
Platform: any
Requires-Python: >=3.7
Requires-Dist: click
